protocol/__init__.py
protocol/_version.py
protocol/base.py
protocol/config.py
protocol/imaging.py
protocol/utils.py
protocol/tests/.DS_Store
protocol/tests/__init__.py
protocol/tests/conftest.py
protocol/tests/test_base_protocol.py
protocol/tests/test_base_sequence.py
protocol/tests/test_bidsimaging_sequence.py
protocol/tests/test_imaging.py
protocol/tests/test_sequence.py
protocol/tests/utils.py
protocol/tests/resources/MRBRAIN.DCM
protocol/tests/resources/epi_pe_ap-00001.dcm
protocol/tests/resources/sample.json
protocol-0.35.dist-info/METADATA
protocol-0.35.dist-info/WHEEL
protocol-0.35.dist-info/licenses/AUTHORS.rst
protocol-0.35.dist-info/licenses/LICENSE
protocol-0.35.dist-info/RECORD
