Metadata-Version: 2.1
Name: protocol
Version: 0.35
Summary: generic framework to develop protocols with implementations in neuroscience
Project-URL: Homepage, https://github.com/raamana/protocol
Author-email: Pradeep Reddy Raamana <raamana@gmail.com>, Harsh Sinha <harsh.sinha@pitt.edu>
License-Expression: Apache-2.0
License-File: AUTHORS.rst
License-File: LICENSE
Keywords: protocol
Classifier: Intended Audience :: Developers
Classifier: Natural Language :: English
Classifier: Programming Language :: Python :: 3.11
Requires-Python: >=3.8
Requires-Dist: lxml
Requires-Dist: nibabel
Requires-Dist: numpy
Requires-Dist: pydicom
Provides-Extra: test
Requires-Dist: flake8; extra == 'test'
Requires-Dist: hypothesis; extra == 'test'
Requires-Dist: pytest; extra == 'test'
Requires-Dist: requests; extra == 'test'
